[
  {
    "id": "LON-0001",
    "date": "2025-06-25T09:12:00",
    "merchant": "Money added via Apple Pay",
    "amount": "10000",
    "status": "",
    "description": "",
    "secondary": "",
    "location": {
      "lat": 51.5072,
      "lon": -0.1276,
      "address": "London, UK"
    }
  },
  {
    "id": "LON-0002",
    "date": "2025-06-27T08:07:00",
    "merchant": "Gail's Bakery Mayfair",
    "amount": "-9.80",
    "status": "",
    "description": "Flat white & almond croissant",
    "secondary": "-£9.80",
    "location": {
      "lat": 51.5099,
      "lon": -0.1486,
      "address": "4-5 North Audley St, Mayfair, London W1K 6ZD"
    }
  },
  {
    "id": "LON-0003",
    "date": "2025-06-27T12:46:00",
    "merchant": "Hard Rock Cafe London - Old Park Lane",
    "amount": "-28.50",
    "status": "",
    "description": "Burger & drink",
    "secondary": "-£28.50",
    "location": {
      "lat": 51.5049,
      "lon": -0.1497,
      "address": "150 Old Park Ln, London W1K 1QZ"
    }
  },
  {
    "id": "LON-0004",
    "date": "2025-06-27T15:31:00",
    "merchant": "Transport for London",
    "amount": "-5.60",
    "status": "",
    "description": "Contactless Tube (Green Park → Oxford Circus, rtn)",
    "secondary": "-£5.60",
    "location": {
      "lat": 51.5032,
      "lon": -0.1436,
      "address": "Green Park Underground Station, London"
    }
  },
  {
    "id": "LON-0005",
    "date": "2025-06-27T16:04:00",
    "merchant": "Starbucks Oxford Street 75",
    "amount": "-5.15",
    "status": "",
    "description": "Iced latte",
    "secondary": "-£5.15",
    "location": {
      "lat": 51.5151,
      "lon": -0.1407,
      "address": "75 Oxford St, London W1D 2ES"
    }
  },
  {
    "id": "LON-0006",
    "date": "2025-06-27T18:22:00",
    "merchant": "The Rose & Crown Mayfair",
    "amount": "-12.40",
    "status": "",
    "description": "2× pints",
    "secondary": "-£12.40",
    "location": {
      "lat": 51.5078,
      "lon": -0.1474,
      "address": "2 Old Park Ln, London W1K 1QN"
    }
  },
  {
    "id": "LON-0007",
    "date": "2025-06-27T21:11:00",
    "merchant": "The French House Soho",
    "amount": "-19.60",
    "status": "",
    "description": "Round of beers",
    "secondary": "-£19.60",
    "location": {
      "lat": 51.5124,
      "lon": -0.1302,
      "address": "49 Dean St, London W1D 5BG"
    }
  },
  {
    "id": "LON-0008",
    "date": "2025-06-27T23:03:00",
    "merchant": "Swift Soho",
    "amount": "-17.50",
    "status": "",
    "description": "2× cocktails",
    "secondary": "-£17.50",
    "location": {
      "lat": 51.5127,
      "lon": -0.1323,
      "address": "12 Old Compton St, London W1D 4TQ"
    }
  },
  {
    "id": "LON-0009",
    "date": "2025-06-28T08:19:00",
    "merchant": "Caffè Nero - Shepherd Market",
    "amount": "-6.30",
    "status": "",
    "description": "Americano & pastry",
    "secondary": "-£6.30",
    "location": {
      "lat": 51.5058,
      "lon": -0.1467,
      "address": "17 Shepherd Market, London W1J 7PJ"
    }
  },
  {
    "id": "EXT-0001",
    "date": "2025-06-28T09:59:00",
    "merchant": "Transport for London",
    "amount": "-26.58",
    "status": "delayed_transaction",
    "description": "Delayed transaction",
    "secondary": "-£12.80",
    "location": {
      "lat": 51.5032,
      "lon": -0.1436,
      "address": "Green Park Underground Station, London"
    }
  },
  {
    "id": "LON-0010",
    "date": "2025-06-28T11:02:00",
    "merchant": "Transport for London",
    "amount": "-3.50",
    "status": "",
    "description": "Off-peak single (Green Park → Covent Garden)",
    "secondary": "-£3.50",
    "location": {
      "lat": 51.5032,
      "lon": -0.1436,
      "address": "Green Park Underground, London"
    }
  },
  {
    "id": "LON-0011",
    "date": "2025-06-28T13:05:00",
    "merchant": "Dishoom Covent Garden",
    "amount": "-54.00",
    "status": "",
    "description": "Lunch for two",
    "secondary": "-£54.00",
    "location": {
      "lat": 51.5129,
      "lon": -0.1265,
      "address": "12 Upper St Martin's Ln, London WC2H 9FB"
    }
  },
  {
    "id": "LON-0012",
    "date": "2025-06-28T16:12:00",
    "merchant": "Snowflake Gelato Soho",
    "amount": "-4.95",
    "status": "",
    "description": "Gelato",
    "secondary": "-£4.95",
    "location": {
      "lat": 51.5129,
      "lon": -0.1316,
      "address": "44 Wardour St, London W1D 6QZ"
    }
  },
  {
    "id": "LON-0013",
    "date": "2025-06-28T18:08:00",
    "merchant": "Transport for London",
    "amount": "-2.90",
    "status": "",
    "description": "Bus cap-up (Soho → Mayfair)",
    "secondary": "-£2.90",
    "location": {
      "lat": 51.512,
      "lon": -0.1337,
      "address": "Soho, London"
    }
  },
  {
    "id": "LON-0014",
    "date": "2025-06-28T19:06:00",
    "merchant": "Ye Grapes, Shepherd Market",
    "amount": "-11.70",
    "status": "",
    "description": "2× pints",
    "secondary": "-£11.70",
    "location": {
      "lat": 51.506,
      "lon": -0.1465,
      "address": "16 Shepherd Market, London W1J 7QF"
    }
  },
  {
    "id": "LON-0015",
    "date": "2025-06-28T22:41:00",
    "merchant": "Bar Soho",
    "amount": "-29.60",
    "status": "",
    "description": "Cocktails",
    "secondary": "-£29.60",
    "location": {
      "lat": 51.5136,
      "lon": -0.1316,
      "address": "23-25 Old Compton St, London W1D 5JL"
    }
  },
  {
    "id": "LON-0016",
    "date": "2025-06-29T08:03:00",
    "merchant": "Pret A Manger - Park Lane",
    "amount": "-5.85",
    "status": "",
    "description": "Breakfast to-go",
    "secondary": "-£5.85",
    "location": {
      "lat": 51.5056,
      "lon": -0.1515,
      "address": "1 Park Ln, London W1K 1QW"
    }
  },
  {
    "id": "LON-0017",
    "date": "2025-06-29T11:37:00",
    "merchant": "Transport for London",
    "amount": "-6.10",
    "status": "",
    "description": "Zone 1-2 off-peak travel",
    "secondary": "-£6.10",
    "location": {
      "lat": 51.515,
      "lon": -0.141,
      "address": "Oxford Circus Underground, London"
    }
  },
  {
    "id": "LON-0018",
    "date": "2025-06-29T13:22:00",
    "merchant": "Nando's Marylebone",
    "amount": "-18.40",
    "status": "",
    "description": "Lunch",
    "secondary": "-£18.40",
    "location": {
      "lat": 51.5204,
      "lon": -0.1555,
      "address": "113 Marylebone High St, London W1U 4SD"
    }
  },
  {
    "id": "LON-0019",
    "date": "2025-06-29T16:05:00",
    "merchant": "Lola's Cupcakes - Selfridges",
    "amount": "-7.80",
    "status": "",
    "description": "Cupcakes",
    "secondary": "-£7.80",
    "location": {
      "lat": 51.5145,
      "lon": -0.1527,
      "address": "400 Oxford St, London W1A 1AB"
    }
  },
  {
    "id": "LON-0020",
    "date": "2025-06-29T19:18:00",
    "merchant": "The Spread Eagle, Soho",
    "amount": "-22.50",
    "status": "",
    "description": "Round of drinks",
    "secondary": "-£22.50",
    "location": {
      "lat": 51.515,
      "lon": -0.1345,
      "address": "8-10 Woodstock St, London"
    }
  },
  {
    "id": "LON-0021",
    "date": "2025-06-30T08:14:00",
    "merchant": "Costa Coffee - Heathrow T2 Arrivals",
    "amount": "-6.90",
    "status": "",
    "description": "Latte & croissant (pre-flight)",
    "secondary": "-£6.90",
    "location": {
      "lat": 51.4703,
      "lon": -0.4543,
      "address": "Heathrow Terminal 2 Arrivals, TW6 1EW"
    }
  },
  {
    "id": "DUB-0001",
    "date": "2025-06-30T12:52:00",
    "merchant": "Taxis Combined Dublin",
    "amount": "-32.00",
    "status": "",
    "description": "DUB → city",
    "secondary": "-€32.00",
    "location": {
      "lat": 53.4264,
      "lon": -6.2499,
      "address": "Dublin Airport, Ireland"
    }
  },
  {
    "id": "DUB-0002",
    "date": "2025-06-30T20:47:00",
    "merchant": "The Temple Bar Pub",
    "amount": "-18.70",
    "status": "",
    "description": "Evening drinks",
    "secondary": "-€18.70",
    "location": {
      "lat": 53.3456,
      "lon": -6.2633,
      "address": "47-48 Temple Bar, Dublin 2"
    }
  },
  {
    "id": "DUB-0003",
    "date": "2025-07-01T11:58:00",
    "merchant": "The Stag's Head",
    "amount": "-24.50",
    "status": "",
    "description": "Pub lunch (paid for family)",
    "secondary": "-€24.50",
    "location": {
      "lat": 53.3439,
      "lon": -6.2623,
      "address": "1 Dame Ct, Dublin 2"
    }
  },
  {
    "id": "DUB-0004",
    "date": "2025-07-01T21:36:00",
    "merchant": "The Brazen Head",
    "amount": "-16.00",
    "status": "",
    "description": "Evening pints",
    "secondary": "-€16.00",
    "location": {
      "lat": 53.3459,
      "lon": -6.2738,
      "address": "20 Lower Bridge St, Dublin 8"
    }
  },
  {
    "id": "DUB-0005",
    "date": "2025-07-02T10:09:00",
    "merchant": "Butlers Chocolate Café - Grafton St",
    "amount": "-6.10",
    "status": "",
    "description": "Coffees",
    "secondary": "-€6.10",
    "location": {
      "lat": 53.3426,
      "lon": -6.2597,
      "address": "51 Grafton St, Dublin 2"
    }
  },
  {
    "id": "DUB-0006",
    "date": "2025-07-02T13:02:00",
    "merchant": "Guinness Storehouse Tickets",
    "amount": "-50.00",
    "status": "",
    "description": "Tour for two",
    "secondary": "-€50.00",
    "location": {
      "lat": 53.3419,
      "lon": -6.2869,
      "address": "St. James's Gate, Dublin 8"
    }
  },
  {
    "id": "DUB-0007",
    "date": "2025-07-02T14:51:00",
    "merchant": "Gravity Bar - Guinness",
    "amount": "-11.00",
    "status": "",
    "description": "2× pints",
    "secondary": "-€11.00",
    "location": {
      "lat": 53.3421,
      "lon": -6.2864,
      "address": "St. James's Gate, Dublin 8"
    }
  },
  {
    "id": "DUB-0008",
    "date": "2025-07-02T19:46:00",
    "merchant": "The Church Café Bar",
    "amount": "-27.80",
    "status": "",
    "description": "Dinner & drinks",
    "secondary": "-€27.80",
    "location": {
      "lat": 53.3486,
      "lon": -6.2656,
      "address": "Jervis St, Dublin 1"
    }
  },
  {
    "id": "DUB-0009",
    "date": "2025-07-03T15:41:00",
    "merchant": "Grogan's Castle Lounge",
    "amount": "-15.40",
    "status": "",
    "description": "Afternoon pints",
    "secondary": "-€15.40",
    "location": {
      "lat": 53.3407,
      "lon": -6.262,
      "address": "15 William St S, Dublin 2"
    }
  },
  {
    "id": "DUB-0010",
    "date": "2025-07-03T22:14:00",
    "merchant": "O'Donoghue's",
    "amount": "-22.00",
    "status": "",
    "description": "Live music & drinks",
    "secondary": "-€22.00",
    "location": {
      "lat": 53.337,
      "lon": -6.2535,
      "address": "15 Merrion Row, Dublin 2"
    }
  },
  {
    "id": "DUB-0011",
    "date": "2025-07-04T09:03:00",
    "merchant": "Circle K Athlone",
    "amount": "-64.20",
    "status": "",
    "description": "Fuel for day trip west",
    "secondary": "-€64.20",
    "location": {
      "lat": 53.423,
      "lon": -7.9362,
      "address": "Dublin Rd, Athlone"
    }
  },
  {
    "id": "DUB-0012",
    "date": "2025-07-04T12:21:00",
    "merchant": "Kylemore Abbey & Gardens",
    "amount": "-28.00",
    "status": "",
    "description": "Entry x2",
    "secondary": "-€28.00",
    "location": {
      "lat": 53.5613,
      "lon": -9.887,
      "address": "Pollacapall, Connemara, Co. Galway"
    }
  },
  {
    "id": "DUB-0013",
    "date": "2025-07-04T13:17:00",
    "merchant": "Kylemore Café",
    "amount": "-21.00",
    "status": "",
    "description": "Lunch",
    "secondary": "-€21.00",
    "location": {
      "lat": 53.5611,
      "lon": -9.8865,
      "address": "Kylemore Abbey, Co. Galway"
    }
  },
  {
    "id": "DUB-0014",
    "date": "2025-07-04T16:02:00",
    "merchant": "Lowry's Bar Clifden",
    "amount": "-33.70",
    "status": "",
    "description": "Round of drinks",
    "secondary": "-€33.70",
    "location": {
      "lat": 53.4883,
      "lon": -10.0197,
      "address": "Market St, Clifden, Co. Galway"
    }
  },
  {
    "id": "DUB-0015",
    "date": "2025-07-05T07:48:00",
    "merchant": "Heuston Station - Coffee Dock",
    "amount": "-4.50",
    "status": "",
    "description": "Pre-flight coffee",
    "secondary": "-€4.50",
    "location": {
      "lat": 53.3467,
      "lon": -6.2924,
      "address": "St John's Rd W, Dublin 8"
    }
  },
  {
    "id": "DUB-0016",
    "date": "2025-07-05T09:10:00",
    "merchant": "Heathrow Express",
    "amount": "-25.00",
    "status": "",
    "description": "Heathrow → Paddington",
    "secondary": "-£25.00",
    "location": {
      "lat": 51.47,
      "lon": -0.4543,
      "address": "Heathrow Airport, London"
    }
  },
  {
    "id": "HMP-0001",
    "date": "2025-07-05T18:12:00",
    "merchant": "Marks & Spencer Simply Food",
    "amount": "-12.75",
    "status": "",
    "description": "Groceries",
    "secondary": "-£12.75",
    "location": {
      "lat": 51.5556,
      "lon": -0.1754,
      "address": "Hampstead, London NW3"
    }
  },
  {
    "id": "EXT-0002",
    "date": "2025-07-06T01:00:00",
    "merchant": "Money added via Apple Pay",
    "amount": "1100",
    "status": "",
    "description": "",
    "secondary": "",
    "location": {
      "lat": null,
      "lon": null,
      "address": "Online"
    }
  },
  {
    "id": "HMP-0002",
    "date": "2025-07-06T08:36:00",
    "merchant": "Gail's Bakery Hampstead",
    "amount": "-9.80",
    "status": "",
    "description": "Breakfast for two",
    "secondary": "-£9.80",
    "location": {
      "lat": 51.5567,
      "lon": -0.1781,
      "address": "64 Hampstead High St, NW3 1QH"
    }
  },
  {
    "id": "HMP-0003",
    "date": "2025-07-06T12:41:00",
    "merchant": "Camden Market Food Stalls",
    "amount": "-15.00",
    "status": "",
    "description": "Street food lunch",
    "secondary": "-£15.00",
    "location": {
      "lat": 51.5416,
      "lon": -0.1469,
      "address": "Camden Lock Pl, NW1 8AF"
    }
  },
  {
    "id": "HMP-0004",
    "date": "2025-07-06T17:22:00",
    "merchant": "Waterstones Hampstead",
    "amount": "-23.00",
    "status": "",
    "description": "Books",
    "secondary": "-£23.00",
    "location": {
      "lat": 51.5564,
      "lon": -0.1785,
      "address": "68-69 Hampstead High St, NW3 1QX"
    }
  },
  {
    "id": "HMP-0005",
    "date": "2025-07-07T08:11:00",
    "merchant": "Gail's Bakery Hampstead",
    "amount": "-7.60",
    "status": "",
    "description": "Cappuccino & pastry",
    "secondary": "-£7.60",
    "location": {
      "lat": 51.5567,
      "lon": -0.1781,
      "address": "64 Hampstead High St, NW3 1QH"
    }
  },
  {
    "id": "HMP-0006",
    "date": "2025-07-07T10:24:00",
    "merchant": "Transport for London",
    "amount": "-2.80",
    "status": "",
    "description": "Northern line (Hampstead → Tottenham Ct Rd)",
    "secondary": "-£2.80",
    "location": {
      "lat": 51.5561,
      "lon": -0.178,
      "address": "Hampstead Station, NW3 1QG"
    }
  },
  {
    "id": "HMP-0007",
    "date": "2025-07-07T13:05:00",
    "merchant": "Selfridges & Co.",
    "amount": "-358.00",
    "status": "",
    "description": "Designer clothing",
    "secondary": "-£358.00",
    "location": {
      "lat": 51.5145,
      "lon": -0.1527,
      "address": "400 Oxford St, W1A 1AB"
    }
  },
  {
    "id": "HMP-0008",
    "date": "2025-07-07T18:34:00",
    "merchant": "Pizza Express Hampstead",
    "amount": "-29.50",
    "status": "",
    "description": "Dinner",
    "secondary": "-£29.50",
    "location": {
      "lat": 51.5571,
      "lon": -0.1789,
      "address": "70 Heath St, NW3 1DN"
    }
  },
  {
    "id": "HMP-0009",
    "date": "2025-07-07T20:54:00",
    "merchant": "Transport for London",
    "amount": "-2.10",
    "status": "",
    "description": "Bus (Hampstead → Swiss Cottage)",
    "secondary": "-£2.10",
    "location": {
      "lat": 51.5501,
      "lon": -0.179,
      "address": "Hampstead, London"
    }
  },
  {
    "id": "EXT-0003",
    "date": "2025-07-07T23:02:00",
    "merchant": "Transport for London",
    "amount": "0",
    "status": "card_verification",
    "description": "Card verification",
    "secondary": "",
    "location": {
      "lat": 51.5561,
      "lon": -0.178,
      "address": "Hampstead Station, London"
    }
  },
  {
    "id": "HMP-0010",
    "date": "2025-07-08T08:24:00",
    "merchant": "Gail's Bakery Hampstead",
    "amount": "-8.40",
    "status": "",
    "description": "Latte & bun",
    "secondary": "-£8.40",
    "location": {
      "lat": 51.5567,
      "lon": -0.1781,
      "address": "64 Hampstead High St, NW3 1QH"
    }
  },
  {
    "id": "HMP-0011",
    "date": "2025-07-08T12:58:00",
    "merchant": "Pret A Manger South Kensington",
    "amount": "-13.75",
    "status": "",
    "description": "Lunch for two",
    "secondary": "-£13.75",
    "location": {
      "lat": 51.4955,
      "lon": -0.1749,
      "address": "Exhibition Rd, SW7"
    }
  },
  {
    "id": "EXT-0004",
    "date": "2025-07-08T13:33:00",
    "merchant": "Money added via Apple Pay",
    "amount": "50",
    "status": "",
    "description": "",
    "secondary": "",
    "location": {
      "lat": null,
      "lon": null,
      "address": "Online"
    }
  },
  {
    "id": "HMP-0012",
    "date": "2025-07-08T16:36:00",
    "merchant": "Transport for London",
    "amount": "-3.20",
    "status": "",
    "description": "Tube (South Kensington → Hampstead)",
    "secondary": "-£3.20",
    "location": {
      "lat": 51.494,
      "lon": -0.1736,
      "address": "South Kensington Station, SW7 2NB"
    }
  },
  {
    "id": "HMP-0013",
    "date": "2025-07-08T18:12:00",
    "merchant": "Uber London",
    "amount": "-18.60",
    "status": "",
    "description": "West End → Hampstead",
    "secondary": "-£18.60",
    "location": {
      "lat": 51.5095,
      "lon": -0.1337,
      "address": "Soho, London"
    }
  },
  {
    "id": "HMP-0014",
    "date": "2025-07-09T09:02:00",
    "merchant": "Waitrose & Partners Finchley Rd",
    "amount": "-24.35",
    "status": "",
    "description": "Groceries",
    "secondary": "-£24.35",
    "location": {
      "lat": 51.5479,
      "lon": -0.1798,
      "address": "O2 Centre, 255 Finchley Rd, NW3 6LU"
    }
  },
  {
    "id": "EXT-0007",
    "date": "2025-07-09T10:24:00",
    "merchant": "Waitrose",
    "amount": "-16.25",
    "status": "",
    "description": "",
    "secondary": "-£7.90",
    "location": {
      "lat": 51.5479,
      "lon": -0.1798,
      "address": "Waitrose & Partners, 255 Finchley Rd, London NW3 6LU"
    }
  },
  {
    "id": "HMP-0015",
    "date": "2025-07-09T19:28:00",
    "merchant": "The Ivy Asia St Paul's",
    "amount": "-423.00",
    "status": "",
    "description": "Dinner for two",
    "secondary": "-£423.00",
    "location": {
      "lat": 51.5139,
      "lon": -0.0982,
      "address": "20 New Change, London EC4M 9AG"
    }
  },
  {
    "id": "HMP-0016",
    "date": "2025-07-09T22:11:00",
    "merchant": "BrewDog Soho",
    "amount": "-14.80",
    "status": "",
    "description": "Beers",
    "secondary": "-£14.80",
    "location": {
      "lat": 51.5133,
      "lon": -0.1349,
      "address": "21-22 Poland St, W1F 8QQ"
    }
  },
  {
    "id": "HMP-0017",
    "date": "2025-07-10T08:07:00",
    "merchant": "Gail's Bakery Hampstead",
    "amount": "-7.95",
    "status": "",
    "description": "Breakfast",
    "secondary": "-£7.95",
    "location": {
      "lat": 51.5567,
      "lon": -0.1781,
      "address": "64 Hampstead High St, NW3 1QH"
    }
  },
  {
    "id": "EXT-0006",
    "date": "2025-07-10T09:32:00",
    "merchant": "South Western Railway",
    "amount": "-81.60",
    "status": "",
    "description": "",
    "secondary": "-£39.60",
    "location": {
      "lat": 51.5033,
      "lon": -0.1133,
      "address": "London Waterloo Station"
    }
  },
  {
    "id": "HMP-0018",
    "date": "2025-07-10T20:14:00",
    "merchant": "Alain Ducasse at The Dorchester",
    "amount": "-593.00",
    "status": "",
    "description": "Dinner for two",
    "secondary": "-£593.00",
    "location": {
      "lat": 51.507,
      "lon": -0.1517,
      "address": "53 Park Ln, London W1K 1QA"
    }
  },
  {
    "id": "HMP-0019",
    "date": "2025-07-10T22:02:00",
    "merchant": "The Dorchester Bar",
    "amount": "-35.00",
    "status": "",
    "description": "Post-dinner drinks",
    "secondary": "-£35.00",
    "location": {
      "lat": 51.5071,
      "lon": -0.1516,
      "address": "53 Park Ln, London W1K 1QA"
    }
  },
  {
    "id": "ITA-0001",
    "date": "2025-07-14T06:48:00",
    "merchant": "Addison Lee",
    "amount": "-65.00",
    "status": "",
    "description": "Ride to Heathrow",
    "secondary": "-£65.00",
    "location": {
      "lat": 51.52,
      "lon": -0.1347,
      "address": "London, UK"
    }
  },
  {
    "id": "EXT-0005",
    "date": "2025-07-14T08:30:00",
    "merchant": "WHSmith",
    "amount": "-51.49",
    "status": "",
    "description": "",
    "secondary": "-£24.99",
    "location": {
      "lat": 51.47,
      "lon": -0.4543,
      "address": "WHSmith, Heathrow Terminal 5, London"
    }
  },
  {
    "id": "ITA-0002",
    "date": "2025-07-14T09:02:00",
    "merchant": "Caffè Nero - Heathrow T5A",
    "amount": "-7.40",
    "status": "",
    "description": "Latte & pastry",
    "secondary": "-£7.40",
    "location": {
      "lat": 51.47,
      "lon": -0.4543,
      "address": "Heathrow Terminal 5, TW6 2GA"
    }
  },
  {
    "id": "ITA-0003",
    "date": "2025-07-14T15:26:00",
    "merchant": "Taxi Roma NCC",
    "amount": "-52.00",
    "status": "",
    "description": "FCO → Hotel",
    "secondary": "-€52.00",
    "location": {
      "lat": 41.7999,
      "lon": 12.2463,
      "address": "Rome Fiumicino Airport"
    }
  },
  {
    "id": "ITA-0004",
    "date": "2025-07-14T16:18:00",
    "merchant": "Hotel Eden Roma",
    "amount": "-900.00",
    "status": "",
    "description": "Room charge (1 night)",
    "secondary": "-€900.00",
    "location": {
      "lat": 41.9056,
      "lon": 12.4865,
      "address": "Via Ludovisi 49, 00187 Roma"
    }
  },
  {
    "id": "ITA-0005",
    "date": "2025-07-14T20:02:00",
    "merchant": "Armando al Pantheon",
    "amount": "-134.00",
    "status": "",
    "description": "Dinner for two",
    "secondary": "-€134.00",
    "location": {
      "lat": 41.8991,
      "lon": 12.4769,
      "address": "Salita dei Crescenzi 31, Roma"
    }
  },
  {
    "id": "EXT-0017",
    "date": "2025-07-15T08:00:00",
    "merchant": "yesim",
    "amount": "-12.59",
    "status": "",
    "description": "",
    "secondary": "-€7",
    "location": {
      "lat": null,
      "lon": null,
      "address": "Online (eSIM)"
    }
  },
  {
    "id": "ITA-0006",
    "date": "2025-07-15T08:21:00",
    "merchant": "Trenitalia",
    "amount": "-48.00",
    "status": "",
    "description": "Frecciarossa Rome→Naples (2 seats, mixed fares)",
    "secondary": "-€48.00",
    "location": {
      "lat": 41.9028,
      "lon": 12.5016,
      "address": "Roma Termini"
    }
  },
  {
    "id": "ITA-0007",
    "date": "2025-07-15T10:42:00",
    "merchant": "Caffè Vergnano 1882",
    "amount": "-8.50",
    "status": "",
    "description": "Coffees at Napoli Centrale",
    "secondary": "-€8.50",
    "location": {
      "lat": 40.852,
      "lon": 14.2728,
      "address": "P.zza Garibaldi, Napoli"
    }
  },
  {
    "id": "ITA-0008",
    "date": "2025-07-15T11:06:00",
    "merchant": "EAV Circumvesuviana",
    "amount": "-7.20",
    "status": "",
    "description": "Napoli→Pompei (2 tickets)",
    "secondary": "-€7.20",
    "location": {
      "lat": 40.8506,
      "lon": 14.2723,
      "address": "Napoli Garibaldi"
    }
  },
  {
    "id": "ITA-0009",
    "date": "2025-07-15T12:03:00",
    "merchant": "Parco Archeologico di Pompei",
    "amount": "-30.00",
    "status": "",
    "description": "Entry x2",
    "secondary": "-€30.00",
    "location": {
      "lat": 40.7497,
      "lon": 14.4871,
      "address": "Piazza Esedra, Pompei"
    }
  },
  {
    "id": "EXT-0009",
    "date": "2025-07-15T12:05:00",
    "merchant": "Scavi di Pompei",
    "amount": "-39.51",
    "status": "",
    "description": "",
    "secondary": "-€22",
    "location": {
      "lat": 40.7499,
      "lon": 14.4872,
      "address": "Scavi di Pompei Ticket Office"
    }
  },
  {
    "id": "EXT-0008",
    "date": "2025-07-15T13:12:00",
    "merchant": "Bookshop Pompeii Op. La",
    "amount": "-2.70",
    "status": "",
    "description": "",
    "secondary": "-€1.50",
    "location": {
      "lat": 40.7497,
      "lon": 14.4871,
      "address": "Bookshop, Parco Archeologico di Pompei"
    }
  },
  {
    "id": "EXT-0011",
    "date": "2025-07-15T16:02:00",
    "merchant": "Suisse Pompei",
    "amount": "-10.77",
    "status": "",
    "description": "",
    "secondary": "-€6",
    "location": {
      "lat": 40.7492,
      "lon": 14.4869,
      "address": "Piazza Esedra, Pompei"
    }
  },
  {
    "id": "ITA-0010",
    "date": "2025-07-15T17:01:00",
    "merchant": "Taxi Pompei - Sorrento",
    "amount": "-95.00",
    "status": "",
    "description": "Private transfer",
    "secondary": "-€95.00",
    "location": {
      "lat": 40.7459,
      "lon": 14.4974,
      "address": "Pompei, NA"
    }
  },
  {
    "id": "ITA-0011",
    "date": "2025-07-15T20:19:00",
    "merchant": "L'Antica Trattoria Sorrento",
    "amount": "-160.00",
    "status": "",
    "description": "Dinner for two",
    "secondary": "-€160.00",
    "location": {
      "lat": 40.6269,
      "lon": 14.3752,
      "address": "Via Padre Reginaldo Giuliani 33, Sorrento"
    }
  },
  {
    "id": "ITA-0012",
    "date": "2025-07-16T08:31:00",
    "merchant": "Pasticceria Primavera",
    "amount": "-14.00",
    "status": "",
    "description": "Breakfast",
    "secondary": "-€14.00",
    "location": {
      "lat": 40.6262,
      "lon": 14.3753,
      "address": "Corso Italia 142, Sorrento"
    }
  },
  {
    "id": "ITA-0013",
    "date": "2025-07-16T12:47:00",
    "merchant": "Fauno Bar",
    "amount": "-45.00",
    "status": "",
    "description": "Lunch",
    "secondary": "-€45.00",
    "location": {
      "lat": 40.6267,
      "lon": 14.3757,
      "address": "Piazza Tasso 13/15, Sorrento"
    }
  },
  {
    "id": "EXT-0010",
    "date": "2025-07-16T13:50:00",
    "merchant": "Photo Aminta Sorrento",
    "amount": "-33.18",
    "status": "",
    "description": "",
    "secondary": "-€18.50",
    "location": {
      "lat": 40.6269,
      "lon": 14.3756,
      "address": "Via Correale, Sorrento"
    }
  },
  {
    "id": "ITA-0014",
    "date": "2025-07-16T19:56:00",
    "merchant": "Ristorante Il Buco",
    "amount": "-210.00",
    "status": "",
    "description": "Dinner for two",
    "secondary": "-€210.00",
    "location": {
      "lat": 40.6272,
      "lon": 14.3738,
      "address": "2a Rampa Marina Piccola, Sorrento"
    }
  },
  {
    "id": "ITA-0015",
    "date": "2025-07-17T09:03:00",
    "merchant": "Grand Hotel Excelsior Vittoria",
    "amount": "-80.00",
    "status": "",
    "description": "City tax (2 nights)",
    "secondary": "-€80.00",
    "location": {
      "lat": 40.626,
      "lon": 14.3737,
      "address": "Piazza Tasso 34, Sorrento"
    }
  },
  {
    "id": "ITA-0016",
    "date": "2025-07-17T10:42:00",
    "merchant": "Alilauro Hydrofoil",
    "amount": "-58.00",
    "status": "",
    "description": "Sorrento→Positano (2 tickets)",
    "secondary": "-€58.00",
    "location": {
      "lat": 40.6269,
      "lon": 14.3752,
      "address": "Marina Piccola, Sorrento"
    }
  },
  {
    "id": "ITA-0017",
    "date": "2025-07-17T12:09:00",
    "merchant": "Covo Dei Saraceni Beach Club",
    "amount": "-50.00",
    "status": "",
    "description": "Sunbeds & umbrella",
    "secondary": "-€50.00",
    "location": {
      "lat": 40.6285,
      "lon": 14.4858,
      "address": "Via Regina Giovanna, Positano"
    }
  },
  {
    "id": "ITA-0018",
    "date": "2025-07-17T15:17:00",
    "merchant": "Chez Black",
    "amount": "-124.00",
    "status": "",
    "description": "Lunch for two",
    "secondary": "-€124.00",
    "location": {
      "lat": 40.628,
      "lon": 14.4863,
      "address": "Via del Brigantino 19, Positano"
    }
  },
  {
    "id": "ITA-0019",
    "date": "2025-07-17T17:41:00",
    "merchant": "Pasticceria La Zagara",
    "amount": "-15.50",
    "status": "",
    "description": "Pastries & drinks",
    "secondary": "-€15.50",
    "location": {
      "lat": 40.6285,
      "lon": 14.4869,
      "address": "Via dei Mulini 8, Positano"
    }
  },
  {
    "id": "ITA-0020",
    "date": "2025-07-17T18:36:00",
    "merchant": "Hotel Palazzo Murat",
    "amount": "-2842.00",
    "status": "",
    "description": "Room charge 2 nights @ €1421/nt",
    "secondary": "-€2,842.00",
    "location": {
      "lat": 40.6287,
      "lon": 14.4867,
      "address": "Via dei Mulini 23, Positano"
    }
  },
  {
    "id": "ITA-0021",
    "date": "2025-07-17T21:09:00",
    "merchant": "La Sponda - Le Sirenuse",
    "amount": "-398.00",
    "status": "",
    "description": "Dinner for two",
    "secondary": "-€398.00",
    "location": {
      "lat": 40.6292,
      "lon": 14.4863,
      "address": "Via Cristoforo Colombo 30, Positano"
    }
  },
  {
    "id": "ITA-0022",
    "date": "2025-07-18T08:48:00",
    "merchant": "Bar Pasticceria Collina",
    "amount": "-22.00",
    "status": "",
    "description": "Breakfast",
    "secondary": "-€22.00",
    "location": {
      "lat": 40.6283,
      "lon": 14.4872,
      "address": "Via dei Mulini 1, Positano"
    }
  },
  {
    "id": "TOP-0002",
    "date": "2025-07-18T10:12:00",
    "merchant": "Money added via Apple Pay",
    "amount": "10000",
    "status": "",
    "description": "",
    "secondary": "",
    "location": {
      "lat": 40.6287,
      "lon": 14.4867,
      "address": "Positano, SA, Italy"
    }
  },
  {
    "id": "EXT-0013",
    "date": "2025-07-18T10:44:00",
    "merchant": "Consortium 'Unico Campania'",
    "amount": "-2.69",
    "status": "",
    "description": "",
    "secondary": "-€1.50",
    "location": {
      "lat": 40.627,
      "lon": 14.375,
      "address": "Sorrento Station, Campania"
    }
  },
  {
    "id": "EXT-0014",
    "date": "2025-07-18T10:45:00",
    "merchant": "Consortium 'Unico Campania'",
    "amount": "-5.38",
    "status": "",
    "description": "",
    "secondary": "-€3",
    "location": {
      "lat": 40.627,
      "lon": 14.375,
      "address": "Sorrento Station, Campania"
    }
  },
  {
    "id": "EXT-0015",
    "date": "2025-07-18T11:10:00",
    "merchant": "Navigazione Libera Del",
    "amount": "-55.44",
    "status": "",
    "description": "",
    "secondary": "-€31",
    "location": {
      "lat": 40.6282,
      "lon": 14.4865,
      "address": "Molo, Positano"
    }
  },
  {
    "id": "ITA-0023",
    "date": "2025-07-18T12:26:00",
    "merchant": "Arienzo Beach Club",
    "amount": "-76.00",
    "status": "",
    "description": "Lunch & drinks",
    "secondary": "-€76.00",
    "location": {
      "lat": 40.6205,
      "lon": 14.491,
      "address": "Via Arienzo 16, Positano"
    }
  },
  {
    "id": "EXT-0012",
    "date": "2025-07-18T19:10:00",
    "merchant": "SITA SUD",
    "amount": "-8.59",
    "status": "",
    "description": "",
    "secondary": "-€4.80",
    "location": {
      "lat": 40.628,
      "lon": 14.4863,
      "address": "Positano Sponda Bus Stop"
    }
  },
  {
    "id": "ITA-0024",
    "date": "2025-07-18T19:51:00",
    "merchant": "Al Palazzo - Palazzo Murat",
    "amount": "-248.00",
    "status": "",
    "description": "Dinner for two",
    "secondary": "-€248.00",
    "location": {
      "lat": 40.6287,
      "lon": 14.4867,
      "address": "Via dei Mulini 23, Positano"
    }
  },
  {
    "id": "EXT-0016",
    "date": "2025-07-18T22:49:00",
    "merchant": "Bar Buca di Bacco",
    "amount": "-11.63",
    "status": "",
    "description": "",
    "secondary": "-€6.50",
    "location": {
      "lat": 40.6286,
      "lon": 14.4868,
      "address": "Via Rampa Teglia, Positano"
    }
  },
  {
    "id": "ITA-0025",
    "date": "2025-07-19T10:18:00",
    "merchant": "NLG - Navigazione Libera del Golfo",
    "amount": "-72.00",
    "status": "",
    "description": "Ferry Positano→Napoli (2 pax)",
    "secondary": "-€72.00",
    "location": {
      "lat": 40.6282,
      "lon": 14.4865,
      "address": "Molo, Positano"
    }
  },
  {
    "id": "ITA-0026",
    "date": "2025-07-19T12:02:00",
    "merchant": "Taxi Napoli Port - Aeroporto",
    "amount": "-38.00",
    "status": "",
    "description": "Port → NAP",
    "secondary": "-€38.00",
    "location": {
      "lat": 40.8389,
      "lon": 14.2786,
      "address": "Calata Porta di Massa, Napoli"
    }
  },
  {
    "id": "SAR-0001",
    "date": "2025-07-19T21:34:00",
    "merchant": "Uber Trip",
    "amount": "-89.50",
    "status": "",
    "description": "Olbia OLB → Porto Cervo (Uber Black)",
    "secondary": "-€89.50",
    "location": {
      "lat": 40.8987,
      "lon": 9.5176,
      "address": "Olbia Costa Smeralda Airport"
    }
  },
  {
    "id": "SAR-ZUMA-0001",
    "date": "2025-07-19T21:56:00",
    "merchant": "Zuma Porto Cervo",
    "amount": "-16.00",
    "status": "",
    "description": "Beer",
    "secondary": "-€16.00",
    "location": {
      "lat": 41.1369,
      "lon": 9.5328,
      "address": "Promenade du Port, Via Porto Vecchio, 07021 Porto Cervo, Arzachena SS, Italy"
    }
  },
  {
    "id": "SAR-ZUMA-0002",
    "date": "2025-07-19T22:08:00",
    "merchant": "Zuma Porto Cervo",
    "amount": "-68.00",
    "status": "",
    "description": "Cocktail round (table)",
    "secondary": "-€68.00",
    "location": {
      "lat": 41.1369,
      "lon": 9.5328,
      "address": "Promenade du Port, Via Porto Vecchio, 07021 Porto Cervo"
    }
  },
  {
    "id": "SAR-ZUMA-0003",
    "date": "2025-07-19T22:17:00",
    "merchant": "Zuma Porto Cervo",
    "amount": "-68.00",
    "status": "",
    "description": "Cocktail round",
    "secondary": "-€68.00",
    "location": {
      "lat": 41.1369,
      "lon": 9.5328,
      "address": "Promenade du Port, Via Porto Vecchio, 07021 Porto Cervo"
    }
  },
  {
    "id": "SAR-ZUMA-0004",
    "date": "2025-07-19T22:26:00",
    "merchant": "Zuma Porto Cervo",
    "amount": "-16.00",
    "status": "",
    "description": "Beer",
    "secondary": "-€16.00",
    "location": {
      "lat": 41.1369,
      "lon": 9.5328,
      "address": "Promenade du Port, Via Porto Vecchio, 07021 Porto Cervo"
    }
  },
  {
    "id": "SAR-ZUMA-0005",
    "date": "2025-07-19T22:32:00",
    "merchant": "Zuma Porto Cervo",
    "amount": "-68.00",
    "status": "",
    "description": "Cocktail round",
    "secondary": "-€68.00",
    "location": {
      "lat": 41.1369,
      "lon": 9.5328,
      "address": "Promenade du Port, Via Porto Vecchio, 07021 Porto Cervo"
    }
  },
  {
    "id": "SAR-ZUMA-0006",
    "date": "2025-07-19T22:41:00",
    "merchant": "Zuma Porto Cervo",
    "amount": "-129.00",
    "status": "",
    "description": "Sushi & robata plates",
    "secondary": "-€129.00",
    "location": {
      "lat": 41.1369,
      "lon": 9.5328,
      "address": "Promenade du Port, Via Porto Vecchio, 07021 Porto Cervo"
    }
  },
  {
    "id": "SAR-ZUMA-0007",
    "date": "2025-07-19T22:49:00",
    "merchant": "Zuma Porto Cervo",
    "amount": "-68.00",
    "status": "",
    "description": "Cocktail round",
    "secondary": "-€68.00",
    "location": {
      "lat": 41.1369,
      "lon": 9.5328,
      "address": "Promenade du Port, Via Porto Vecchio, 07021 Porto Cervo"
    }
  },
  {
    "id": "SAR-ZUMA-0008",
    "date": "2025-07-19T22:57:00",
    "merchant": "Zuma Porto Cervo",
    "amount": "-22.05",
    "status": "",
    "description": "Single drink",
    "secondary": "-€22.05",
    "location": {
      "lat": 41.1369,
      "lon": 9.5328,
      "address": "Promenade du Port, Via Porto Vecchio, 07021 Porto Cervo"
    }
  },
  {
    "id": "SAR-ZUMA-0009",
    "date": "2025-07-19T23:05:00",
    "merchant": "Zuma Porto Cervo",
    "amount": "-68.00",
    "status": "",
    "description": "Cocktail round",
    "secondary": "-€68.00",
    "location": {
      "lat": 41.1369,
      "lon": 9.5328,
      "address": "Promenade du Port, Via Porto Vecchio, 07021 Porto Cervo"
    }
  },
  {
    "id": "SAR-ZUMA-0010",
    "date": "2025-07-19T23:14:00",
    "merchant": "Zuma Porto Cervo",
    "amount": "-16.00",
    "status": "",
    "description": "Beer",
    "secondary": "-€16.00",
    "location": {
      "lat": 41.1369,
      "lon": 9.5328,
      "address": "Promenade du Port, Via Porto Vecchio, 07021 Porto Cervo"
    }
  },
  {
    "id": "SAR-ZUMA-0011",
    "date": "2025-07-19T23:22:00",
    "merchant": "Zuma Porto Cervo",
    "amount": "-68.00",
    "status": "",
    "description": "Cocktail round",
    "secondary": "-€68.00",
    "location": {
      "lat": 41.1369,
      "lon": 9.5328,
      "address": "Promenade du Port, Via Porto Vecchio, 07021 Porto Cervo"
    }
  },
  {
    "id": "SAR-ZUMA-0012",
    "date": "2025-07-19T23:31:00",
    "merchant": "Zuma Porto Cervo",
    "amount": "-178.00",
    "status": "",
    "description": "Bottle / premium round",
    "secondary": "-€178.00",
    "location": {
      "lat": 41.1369,
      "lon": 9.5328,
      "address": "Promenade du Port, Via Porto Vecchio, 07021 Porto Cervo"
    }
  },
  {
    "id": "SAR-ZUMA-0013",
    "date": "2025-07-19T23:44:00",
    "merchant": "Zuma Porto Cervo",
    "amount": "-22.05",
    "status": "",
    "description": "Single drink",
    "secondary": "-€22.05",
    "location": {
      "lat": 41.1369,
      "lon": 9.5328,
      "address": "Promenade du Port, Via Porto Vecchio, 07021 Porto Cervo"
    }
  },
  {
    "id": "SAR-ZUMA-0014",
    "date": "2025-07-19T23:52:00",
    "merchant": "Zuma Porto Cervo",
    "amount": "-68.00",
    "status": "",
    "description": "Cocktail round",
    "secondary": "-€68.00",
    "location": {
      "lat": 41.1369,
      "lon": 9.5328,
      "address": "Promenade du Port, Via Porto Vecchio, 07021 Porto Cervo"
    }
  },
  {
    "id": "SAR-ZUMA-0015",
    "date": "2025-07-19T23:58:00",
    "merchant": "Zuma Porto Cervo",
    "amount": "-247.99",
    "status": "",
    "description": "Late-night bar tab close",
    "secondary": "-€247.99",
    "location": {
      "lat": 41.1369,
      "lon": 9.5328,
      "address": "Promenade du Port, Via Porto Vecchio, 07021 Porto Cervo"
    }
  },
  {
    "id": "SAR-0002",
    "date": "2025-07-20T13:09:00",
    "merchant": "Sardinia Boat Charter S.R.L.",
    "amount": "-1004.00",
    "status": "",
    "description": "Private boat hire (Porto Cervo Marina)",
    "secondary": "-€1,004.00",
    "location": {
      "lat": 41.1393,
      "lon": 9.5355,
      "address": "Molo Vecchio, Porto Cervo Marina, Arzachena"
    }
  },
  {
    "id": "SAR-0003",
    "date": "2025-07-20T20:18:00",
    "merchant": "Novikov Porto Cervo",
    "amount": "-310.00",
    "status": "",
    "description": "Dinner for two",
    "secondary": "-€310.00",
    "location": {
      "lat": 41.1397,
      "lon": 9.5338,
      "address": "Piazza del Principe, Porto Cervo"
    }
  },
  {
    "id": "SAR-0004",
    "date": "2025-07-21T10:22:00",
    "merchant": "Cala di Volpe Hotel",
    "amount": "-4200.00",
    "status": "",
    "description": "Room charge 2 nights @ €2100/nt",
    "secondary": "-€4,200.00",
    "location": {
      "lat": 41.1278,
      "lon": 9.5522,
      "address": "Costa Smeralda, 07020 Porto Cervo"
    }
  },
  {
    "id": "SAR-0005",
    "date": "2025-07-21T13:15:00",
    "merchant": "Phi Beach",
    "amount": "-385.00",
    "status": "",
    "description": "Beach club lunch & drinks",
    "secondary": "-€385.00",
    "location": {
      "lat": 41.2047,
      "lon": 9.3914,
      "address": "Baja Sardinia, 07021 Arzachena SS"
    }
  },
  {
    "id": "EXT-0018",
    "date": "2025-07-21T14:30:00",
    "merchant": "ARST",
    "amount": "-5.62",
    "status": "",
    "description": "",
    "secondary": "-€3.10",
    "location": {
      "lat": 41.1352,
      "lon": 9.5276,
      "address": "Fermata ARST, Porto Cervo"
    }
  },
  {
    "id": "SAR-0006",
    "date": "2025-07-21T20:45:00",
    "merchant": "Il Pomodoro Porto Cervo",
    "amount": "-420.00",
    "status": "",
    "description": "Dinner for two",
    "secondary": "-€420.00",
    "location": {
      "lat": 41.1375,
      "lon": 9.5312,
      "address": "Piazzetta, Porto Cervo"
    }
  },
  {
    "id": "SAR-0007",
    "date": "2025-07-22T08:42:00",
    "merchant": "Cala di Volpe - Breakfast",
    "amount": "-98.00",
    "status": "",
    "description": "Breakfast for two",
    "secondary": "-€98.00",
    "location": {
      "lat": 41.1278,
      "lon": 9.5522,
      "address": "Costa Smeralda, 07020 Porto Cervo"
    }
  },
  {
    "id": "SAR-0008",
    "date": "2025-07-22T14:33:00",
    "merchant": "Nikki Beach Costa Smeralda",
    "amount": "-650.00",
    "status": "",
    "description": "Beach club day pass & lunch",
    "secondary": "-€650.00",
    "location": {
      "lat": 41.1083,
      "lon": 9.4667,
      "address": "Località Lido del Sole, 07020 Porto Rotondo"
    }
  },
  {
    "id": "SAR-0009",
    "date": "2025-07-22T21:18:00",
    "merchant": "Matsuhisa Cala di Volpe",
    "amount": "-890.00",
    "status": "",
    "description": "Dinner for two",
    "secondary": "-€890.00",
    "location": {
      "lat": 41.1278,
      "lon": 9.5522,
      "address": "Costa Smeralda, 07020 Porto Cervo"
    }
  },
  {
    "id": "SAR-0010",
    "date": "2025-07-23T11:06:00",
    "merchant": "Helicopter Sardinia",
    "amount": "-2400.00",
    "status": "",
    "description": "Helicopter tour Costa Smeralda",
    "secondary": "-€2,400.00",
    "location": {
      "lat": 41.1369,
      "lon": 9.5328,
      "address": "Porto Cervo Helipad"
    }
  },
  {
    "id": "SAR-0011",
    "date": "2025-07-23T15:27:00",
    "merchant": "Spinnaker Restaurant",
    "amount": "-180.00",
    "status": "",
    "description": "Lunch",
    "secondary": "-€180.00",
    "location": {
      "lat": 41.1381,
      "lon": 9.5341,
      "address": "Porto Cervo Marina"
    }
  },
  {
    "id": "SAR-0012",
    "date": "2025-07-23T19:45:00",
    "merchant": "Taxi Costa Smeralda",
    "amount": "-85.00",
    "status": "",
    "description": "Porto Cervo → Olbia OLB",
    "secondary": "-€85.00",
    "location": {
      "lat": 41.1369,
      "lon": 9.5328,
      "address": "Porto Cervo, SS"
    }
  },
  {
    "id": "FRA-0001",
    "date": "2025-07-24T07:35:00",
    "merchant": "Aéroports de Paris",
    "amount": "-45.00",
    "status": "",
    "description": "CDG→Nice flight connection",
    "secondary": "-€45.00",
    "location": {
      "lat": 49.0097,
      "lon": 2.5479,
      "address": "Charles de Gaulle Airport, 95700 Roissy-en-France"
    }
  },
  {
    "id": "FRA-0002",
    "date": "2025-07-24T13:28:00",
    "merchant": "Taxi Nice Côte d'Azur",
    "amount": "-75.00",
    "status": "",
    "description": "NCE → Antibes",
    "secondary": "-€75.00",
    "location": {
      "lat": 43.665,
      "lon": 7.215,
      "address": "Nice Côte d'Azur Airport"
    }
  },
  {
    "id": "FRA-0003",
    "date": "2025-07-24T14:52:00",
    "merchant": "Hôtel du Cap-Eden-Roc",
    "amount": "-1650.00",
    "status": "",
    "description": "Room charge 1 night",
    "secondary": "-€1,650.00",
    "location": {
      "lat": 43.5531,
      "lon": 7.1272,
      "address": "Boulevard J.F. Kennedy, 06160 Antibes"
    }
  },
  {
    "id": "FRA-0004",
    "date": "2025-07-24T20:15:00",
    "merchant": "La Petite Maison",
    "amount": "-380.00",
    "status": "",
    "description": "Dinner for two",
    "secondary": "-€380.00",
    "location": {
      "lat": 43.6947,
      "lon": 7.2858,
      "address": "11 Rue Saint-François de Paule, 06300 Nice"
    }
  },
  {
    "id": "EXT-0019",
    "date": "2025-07-24T22:57:00",
    "merchant": "RELAY",
    "amount": "-4.81",
    "status": "",
    "description": "",
    "secondary": "-€2.70",
    "location": {
      "lat": 48.8443,
      "lon": 2.373,
      "address": "RELAY, Gare de Lyon, Paris"
    }
  },
  {
    "id": "EXT-0020",
    "date": "2025-07-25T08:45:00",
    "merchant": "CHOPE-MOI Pigalle",
    "amount": "-26.83",
    "status": "",
    "description": "",
    "secondary": "-€15",
    "location": {
      "lat": 48.882,
      "lon": 2.3376,
      "address": "58 Rue Jean-Baptiste Pigalle, 75009 Paris"
    }
  },
  {
    "id": "FRA-0005",
    "date": "2025-07-25T10:18:00",
    "merchant": "Eden-Roc Restaurant",
    "amount": "-165.00",
    "status": "",
    "description": "Breakfast",
    "secondary": "-€165.00",
    "location": {
      "lat": 43.5531,
      "lon": 7.1272,
      "address": "Boulevard J.F. Kennedy, 06160 Antibes"
    }
  },
  {
    "id": "FRA-0006",
    "date": "2025-07-25T16:33:00",
    "merchant": "Galeries Lafayette Nice",
    "amount": "-890.00",
    "status": "",
    "description": "Shopping",
    "secondary": "-€890.00",
    "location": {
      "lat": 43.6955,
      "lon": 7.2711,
      "address": "6 Avenue Jean Médecin, 06000 Nice"
    }
  },
  {
    "id": "FRA-0007",
    "date": "2025-07-25T19:42:00",
    "merchant": "Taxi Nice",
    "amount": "-95.00",
    "status": "",
    "description": "Nice → Paris (TGV station)",
    "secondary": "-€95.00",
    "location": {
      "lat": 43.7034,
      "lon": 7.2663,
      "address": "Nice Ville Station"
    }
  },
  {
    "id": "PAR-0001",
    "date": "2025-07-25T23:18:00",
    "merchant": "SNCF Connect",
    "amount": "-320.00",
    "status": "",
    "description": "TGV Nice→Paris Gare de Lyon",
    "secondary": "-€320.00",
    "location": {
      "lat": 43.7034,
      "lon": 7.2663,
      "address": "Nice Ville, France"
    }
  },
  {
    "id": "PAR-0002",
    "date": "2025-07-26T06:42:00",
    "merchant": "Le Meurice",
    "amount": "-1200.00",
    "status": "",
    "description": "Room charge 1 night",
    "secondary": "-€1,200.00",
    "location": {
      "lat": 48.8647,
      "lon": 2.3278,
      "address": "228 Rue de Rivoli, 75001 Paris"
    }
  },
  {
    "id": "PAR-0003",
    "date": "2025-07-26T08:35:00",
    "merchant": "Café de Flore",
    "amount": "-35.00",
    "status": "",
    "description": "Breakfast",
    "secondary": "-€35.00",
    "location": {
      "lat": 48.8542,
      "lon": 2.332,
      "address": "172 Boulevard Saint-Germain, 75006 Paris"
    }
  },
  {
    "id": "PAR-0004",
    "date": "2025-07-26T12:15:00",
    "merchant": "L'Ami Jean",
    "amount": "-98.00",
    "status": "",
    "description": "Lunch for two",
    "secondary": "-€98.00",
    "location": {
      "lat": 48.8583,
      "lon": 2.3028,
      "address": "27 Rue Malar, 75007 Paris"
    }
  },
  {
    "id": "PAR-0005",
    "date": "2025-07-26T15:47:00",
    "merchant": "Galeries Lafayette Haussmann",
    "amount": "-756.00",
    "status": "",
    "description": "Shopping",
    "secondary": "-€756.00",
    "location": {
      "lat": 48.8738,
      "lon": 2.332,
      "address": "40 Boulevard Haussmann, 75009 Paris"
    }
  },
  {
    "id": "PAR-0006",
    "date": "2025-07-26T18:22:00",
    "merchant": "Taxi G7",
    "amount": "-25.00",
    "status": "",
    "description": "CDG departure transfer",
    "secondary": "-€25.00",
    "location": {
      "lat": 48.8566,
      "lon": 2.3522,
      "address": "Paris, France"
    }
  },
  {
    "id": "PAR-0007",
    "date": "2025-07-26T20:08:00",
    "merchant": "Air France",
    "amount": "-1850.00",
    "status": "",
    "description": "CDG→LHR Business Class",
    "secondary": "-€1,850.00",
    "location": {
      "lat": 49.0097,
      "lon": 2.5479,
      "address": "Charles de Gaulle Airport, 95700 Roissy-en-France"
    }
  }
]